mage/env.py
mage/rendering.py
mage/window.py
gym_mage-0.1.0.dist-info/LICENSE
gym_mage-0.1.0.dist-info/METADATA
gym_mage-0.1.0.dist-info/WHEEL
gym_mage-0.1.0.dist-info/top_level.txt
gym_mage-0.1.0.dist-info/RECORD
