Metadata-Version: 2.1
Name: gym-mage
Version: 0.1.0
Summary: Multi-Agent Grid Environment
Home-page: https://github.com/damat-le/mage
Author: Leo D'Amato
Author-email: leo.damato.dev@gmail.com
Keywords: reinforcement learning,environment,gridworld,agent,rl,openaigym,openai-gym,gym,multi-agent
Classifier: Programming Language :: Python :: 3
Classifier: Operating System :: OS Independent
Requires-Python: >=3.7
License-File: LICENSE
Requires-Dist: numpy
Requires-Dist: matplotlib
